public_meetings/__init__.py
public_meetings/meetings_to_segmentation.py
public_meetings/prepare.py
public_meetings/utils.py
public_meetings/bin/__init__.py
public_meetings/bin/commands.py
public_meetings/data/0b9ec6f049e68d4a35fae75792e2a84e.0.ctm
public_meetings/data/0b9ec6f049e68d4a35fae75792e2a84e.aligned.pckl
public_meetings/data/0b9ec6f049e68d4a35fae75792e2a84e.docx
public_meetings/data/199073d27fc61f6a76cb1f9c1d977aa6.0.ctm
public_meetings/data/199073d27fc61f6a76cb1f9c1d977aa6.1.ctm
public_meetings/data/199073d27fc61f6a76cb1f9c1d977aa6.2.ctm
public_meetings/data/199073d27fc61f6a76cb1f9c1d977aa6.aligned.pckl
public_meetings/data/199073d27fc61f6a76cb1f9c1d977aa6.docx
public_meetings/data/2130e27aed45abb9e7182295fc940cff.0.ctm
public_meetings/data/2130e27aed45abb9e7182295fc940cff.aligned.pckl
public_meetings/data/2130e27aed45abb9e7182295fc940cff.docx
public_meetings/data/2f3f95e2eb2b4532169904b186a8cdf0.0.ctm
public_meetings/data/2f3f95e2eb2b4532169904b186a8cdf0.aligned.pckl
public_meetings/data/2f3f95e2eb2b4532169904b186a8cdf0.docx
public_meetings/data/383fa9579fa610be4a0d1ff531f01006.0.ctm
public_meetings/data/383fa9579fa610be4a0d1ff531f01006.1.ctm
public_meetings/data/383fa9579fa610be4a0d1ff531f01006.2.ctm
public_meetings/data/383fa9579fa610be4a0d1ff531f01006.3.ctm
public_meetings/data/383fa9579fa610be4a0d1ff531f01006.4.ctm
public_meetings/data/383fa9579fa610be4a0d1ff531f01006.5.ctm
public_meetings/data/383fa9579fa610be4a0d1ff531f01006.aligned.pckl
public_meetings/data/383fa9579fa610be4a0d1ff531f01006.docx
public_meetings/data/398ab01c54479bcd841b467dadca1222.0.ctm
public_meetings/data/398ab01c54479bcd841b467dadca1222.1.ctm
public_meetings/data/398ab01c54479bcd841b467dadca1222.aligned.pckl
public_meetings/data/398ab01c54479bcd841b467dadca1222.docx
public_meetings/data/4b926f221e5fb8eac2c24b0a7fca651b.0.ctm
public_meetings/data/4b926f221e5fb8eac2c24b0a7fca651b.aligned.pckl
public_meetings/data/4b926f221e5fb8eac2c24b0a7fca651b.docx
public_meetings-0.1.0rc3.dist-info/LICENSE
public_meetings-0.1.0rc3.dist-info/METADATA
public_meetings-0.1.0rc3.dist-info/WHEEL
public_meetings-0.1.0rc3.dist-info/entry_points.txt
public_meetings-0.1.0rc3.dist-info/top_level.txt
public_meetings-0.1.0rc3.dist-info/RECORD
