Metadata-Version: 2.1
Name: public-meetings
Version: 0.1.0rc3
Summary: A corpus of public meetings
Home-page: UNKNOWN
License: UNKNOWN
Project-URL: Documentation, http://github.com/pltrdy/public_meetings
Project-URL: Source, https://github.com/pltrdy/public_meetings
Platform: UNKNOWN
Requires-Dist: numpy
